ted17/__init__.py
ted17/dategr.py
ted17/db.py
ted17/db_sql.py
ted17/dbmanager.py
ted17/dec.py
ted17/f_find.py
ted17/f_table.py
ted17/grup.py
ted17/parameters.py
ted17/rpt_html.py
ted17/rpt_tbl.py
ted17/rpt_tbl_tst.py
ted17/selector.py
ted17/w_checkbox.py
ted17/w_date.py
ted17/w_date_or_empty.py
ted17/w_integer.py
ted17/w_integer_spin.py
ted17/w_numeric_old.py
ted17/w_numeric_spin.py
ted17/w_text.py
ted17/w_text_button.py
ted17/w_text_button_old.py
ted17/w_text_combo.py
ted17/w_textline.py
ted17/w_textline_numbers_only.py
ted17/w_tree.py
ted17/w_weekdays.py
ted17/w_yesno_combo.py
ted17-0.2.dist-info/DESCRIPTION.rst
ted17-0.2.dist-info/METADATA
ted17-0.2.dist-info/RECORD
ted17-0.2.dist-info/WHEEL
ted17-0.2.dist-info/metadata.json
ted17-0.2.dist-info/top_level.txt
