Metadata-Version: 2.0
Name: ted17
Version: 0.2
Summary: Useful widgets and functions for pyqt development
Home-page: http://tsated.mooo.com/ted17
Author: Ted Lazaros
Author-email: tedlaz@gmail.com
License: MIT
Keywords: PyQt Gui
Platform: any
Classifier: Development Status :: 3 - Alpha
Classifier: License :: OSI Approved :: GNU General Public License v3 (GPLv3)
Classifier: Operating System :: OS Independent
Classifier: Programming Language :: Python
Classifier: Programming Language :: Python :: 2
Classifier: Programming Language :: Python :: 2.7
Classifier: Programming Language :: Python :: 3
Classifier: Programming Language :: Python :: 3.3
Classifier: Programming Language :: Python :: 3.4
Classifier: Programming Language :: Python :: 3.5
Classifier: Programming Language :: Python :: 3.6
Classifier: Topic :: Software Development :: Libraries :: Python Modules
Requires-Dist: PyQt5
